geo/Calculation_gdal.py
geo/Geoserver.py
geo/Style.py
geo/__init__.py
geo/__version__.py
geo/supports.py
geoserver_rest-2.10.0.dist-info/licenses/LICENSE
geoserver_rest-2.10.0.dist-info/METADATA
geoserver_rest-2.10.0.dist-info/WHEEL
geoserver_rest-2.10.0.dist-info/top_level.txt
geoserver_rest-2.10.0.dist-info/RECORD
