Metadata-Version: 2.4
Name: geoserver-rest
Version: 2.10.0
Summary: Package for GeoServer rest API
Home-page: https://github.com/iamtekson/geoserver-rest-python
Author: Tek Kshetri
Author-email: iamtekson@gmail.com
License: MIT License
Keywords: geoserver-rest-python,geoserver rest,python geoserver,geoserver api,api,rest geoserver,python,geoserver python,geoserver rest
Classifier: Programming Language :: Python :: 3
Classifier: Intended Audience :: Developers
Classifier: Intended Audience :: Science/Research
Classifier: License :: OSI Approved :: MIT License
Classifier: Operating System :: OS Independent
Requires-Python: >=3.6
License-File: LICENSE
Requires-Dist: pygments
Requires-Dist: requests
Requires-Dist: xmltodict
Provides-Extra: dev
Requires-Dist: pytest; extra == "dev"
Requires-Dist: black; extra == "dev"
Requires-Dist: flake8; extra == "dev"
Requires-Dist: sphinx>=1.7; extra == "dev"
Requires-Dist: pre-commit; extra == "dev"
Provides-Extra: style
Requires-Dist: matplotlib; extra == "style"
Requires-Dist: seaborn; extra == "style"
Requires-Dist: gdal; extra == "style"
Provides-Extra: all
Requires-Dist: matplotlib; extra == "all"
Requires-Dist: seaborn; extra == "all"
Requires-Dist: gdal; extra == "all"
Dynamic: author
Dynamic: author-email
Dynamic: classifier
Dynamic: description
Dynamic: description-content-type
Dynamic: home-page
Dynamic: keywords
Dynamic: license
Dynamic: license-file
Dynamic: provides-extra
Dynamic: requires-dist
Dynamic: requires-python
Dynamic: summary
